{"data":{"data":[{"year":110,"month":1,"value":8.695652173913043,"numerator":4,"denominator":46},{"year":110,"month":2,"value":18.51851851851852,"numerator":5,"denominator":27},{"year":110,"month":3,"value":10.0,"numerator":3,"denominator":30},{"year":110,"month":4,"value":0.0,"numerator":0,"denominator":34},{"year":110,"month":5,"value":10.81081081081081,"numerator":4,"denominator":37},{"year":110,"month":6,"value":23.52941176470588,"numerator":8,"denominator":34},{"year":110,"month":7,"value":16.27906976744186,"numerator":7,"denominator":43},{"year":110,"month":8,"value":8.16326530612245,"numerator":4,"denominator":49},{"year":110,"month":9,"value":9.523809523809524,"numerator":4,"denominator":42},{"year":110,"month":10,"value":4.081632653061225,"numerator":2,"denominator":49},{"year":110,"month":11,"value":6.521739130434782,"numerator":3,"denominator":46},{"year":110,"month":12,"value":10.416666666666668,"numerator":5,"denominator":48},{"year":111,"month":1,"value":8.333333333333332,"numerator":3,"denominator":36},{"year":111,"month":2,"value":12.195121951219512,"numerator":5,"denominator":41},{"year":111,"month":3,"value":10.9375,"numerator":7,"denominator":64},{"year":111,"month":4,"value":7.575757575757576,"numerator":5,"denominator":66},{"year":111,"month":5,"value":7.894736842105263,"numerator":3,"denominator":38},{"year":111,"month":6,"value":9.210526315789473,"numerator":7,"denominator":76},{"year":111,"month":7,"value":7.792207792207792,"numerator":6,"denominator":77},{"year":111,"month":8,"value":7.4074074074074066,"numerator":4,"denominator":54},{"year":111,"month":9,"value":11.11111111111111,"numerator":6,"denominator":54},{"year":111,"month":10,"value":14.634146341463413,"numerator":12,"denominator":82},{"year":111,"month":11,"value":15.584415584415584,"numerator":12,"denominator":77},{"year":111,"month":12,"value":14.666666666666666,"numerator":11,"denominator":75},{"year":112,"month":1,"value":14.084507042253522,"numerator":10,"denominator":71},{"year":112,"month":2,"value":3.896103896103896,"numerator":3,"denominator":77},{"year":112,"month":3,"value":11.11111111111111,"numerator":10,"denominator":90},{"year":112,"month":4,"value":5.4945054945054945,"numerator":5,"denominator":91},{"year":112,"month":5,"value":10.714285714285714,"numerator":9,"denominator":84},{"year":112,"month":6,"value":5.319148936170213,"numerator":5,"denominator":94},{"year":112,"month":7,"value":8.536585365853659,"numerator":7,"denominator":82},{"year":112,"month":8,"value":3.125,"numerator":3,"denominator":96},{"year":112,"month":9,"value":4.761904761904762,"numerator":4,"denominator":84},{"year":112,"month":10,"value":8.536585365853659,"numerator":7,"denominator":82},{"year":112,"month":11,"value":9.45945945945946,"numerator":7,"denominator":74},{"year":112,"month":12,"value":9.876543209876543,"numerator":8,"denominator":81},{"year":113,"month":1,"value":5.0,"numerator":5,"denominator":100},{"year":113,"month":2,"value":10.95890410958904,"numerator":8,"denominator":73},{"year":113,"month":3,"value":6.593406593406594,"numerator":6,"denominator":91},{"year":113,"month":4,"value":9.090909090909092,"numerator":6,"denominator":66},{"year":113,"month":5,"value":7.0588235294117645,"numerator":6,"denominator":85},{"year":113,"month":6,"value":4.49438202247191,"numerator":4,"denominator":89},{"year":113,"month":7,"value":8.571428571428571,"numerator":6,"denominator":70},{"year":113,"month":8,"value":15.789473684210526,"numerator":12,"denominator":76},{"year":113,"month":9,"value":1.5625,"numerator":1,"denominator":64},{"year":113,"month":10,"value":7.042253521126761,"numerator":5,"denominator":71},{"year":113,"month":11,"value":4.838709677419355,"numerator":3,"denominator":62},{"year":113,"month":12,"value":8.333333333333332,"numerator":6,"denominator":72},{"year":114,"month":1,"value":2.857142857142857,"numerator":2,"denominator":70},{"year":114,"month":2,"value":6.557377049180328,"numerator":4,"denominator":61},{"year":114,"month":3,"value":14.864864864864865,"numerator":11,"denominator":74},{"year":114,"month":4,"value":7.352941176470589,"numerator":5,"denominator":68},{"year":114,"month":5,"value":14.285714285714285,"numerator":9,"denominator":63},{"year":114,"month":6,"value":9.67741935483871,"numerator":6,"denominator":62},{"year":114,"month":7,"value":4.918032786885246,"numerator":3,"denominator":61},{"year":114,"month":8,"value":10.44776119402985,"numerator":7,"denominator":67},{"year":114,"month":9,"value":12.0,"numerator":6,"denominator":50},{"year":114,"month":10,"value":12.121212121212121,"numerator":8,"denominator":66},{"year":114,"month":11,"value":12.280701754385964,"numerator":7,"denominator":57},{"year":114,"month":12,"value":6.329113924050633,"numerator":5,"denominator":79},{"year":115,"month":1,"value":6.329113924050633,"numerator":5,"denominator":79},{"year":115,"month":2,"value":14.925373134328357,"numerator":10,"denominator":67}],"total":62},"summaries":{"data":[{"year":110,"average":10.545048026290397,"benchmark_regional":11.459999999999999,"benchmark_district":13.700000000000001},{"year":111,"average":10.611910910123095,"benchmark_regional":11.99,"benchmark_district":11.959999999999999},{"year":112,"average":7.909645029781502,"benchmark_regional":12.590000000000002,"benchmark_district":12.659999999999998},{"year":113,"average":7.444510344442246,"benchmark_regional":11.99,"benchmark_district":11.959999999999999},{"year":114,"average":9.474356780731288,"benchmark_regional":11.87,"benchmark_district":12.0},{"year":115,"average":10.627243529189496,"benchmark_regional":11.87,"benchmark_district":12.0}],"tcpi":[{"year":113,"medical_center":10.77,"regional_hospital":11.87,"district_hospital":12.0},{"year":114,"medical_center":10.82,"regional_hospital":12.08,"district_hospital":12.33}],"total":6},"analysis":{"status":"warning","anomalies":[{"mechanism":"control_chart","severity":"warning","direction":"unfavorable","message":"超出 2σ 警戒線","value":18.51851851851852,"rule":"rule2_above_2sigma","reference_value":15.271729893915971,"year":110,"month":2},{"mechanism":"control_chart","severity":"alert","direction":"unfavorable","message":"超出管制上限 (UCL=18.63)","value":23.52941176470588,"rule":"rule1_above_ucl","reference_value":18.62615771512545,"year":110,"month":6},{"mechanism":"control_chart","severity":"warning","direction":"unfavorable","message":"超出 2σ 警戒線","value":16.27906976744186,"rule":"rule2_above_2sigma","reference_value":15.271729893915971,"year":110,"month":7},{"mechanism":"control_chart","severity":"warning","direction":"unfavorable","message":"超出 2σ 警戒線","value":15.584415584415584,"rule":"rule2_above_2sigma","reference_value":15.271729893915971,"year":111,"month":11},{"mechanism":"control_chart","severity":"warning","direction":"unfavorable","message":"超出 2σ 警戒線","value":15.789473684210526,"rule":"rule2_above_2sigma","reference_value":14.982271705196675,"year":113,"month":8},{"mechanism":"control_chart","severity":"warning","direction":"unfavorable","message":"3 點中 2 點超出 2σ 上方","value":16.27906976744186,"rule":"rule5_2of3_above","reference_value":15.271729893915971,"year":110,"month":7},{"mechanism":"control_chart","severity":"warning","direction":"unfavorable","message":"3 點中 2 點超出 2σ 上方","value":8.16326530612245,"rule":"rule5_2of3_above","reference_value":15.271729893915971,"year":110,"month":8},{"mechanism":"monthly_change","severity":"watch","direction":"unfavorable","message":"較上月增加 113.0%（不利方向）","value":18.51851851851852,"rule":"","reference_value":8.695652173913043,"year":110,"month":2},{"mechanism":"monthly_change","severity":"excellent","direction":"favorable","message":"較上月減少 46.0%（改善趨勢）","value":10.0,"rule":"","reference_value":18.51851851851852,"year":110,"month":3},{"mechanism":"monthly_change","severity":"excellent","direction":"favorable","message":"較上月減少 100.0%（改善趨勢）","value":0.0,"rule":"","reference_value":10.0,"year":110,"month":4},{"mechanism":"monthly_change","severity":"watch","direction":"unfavorable","message":"較上月增加 117.6%（不利方向）","value":23.52941176470588,"rule":"","reference_value":10.81081081081081,"year":110,"month":6},{"mechanism":"monthly_change","severity":"excellent","direction":"favorable","message":"較上月減少 30.8%（改善趨勢）","value":16.27906976744186,"rule":"","reference_value":23.52941176470588,"year":110,"month":7},{"mechanism":"monthly_change","severity":"excellent","direction":"favorable","message":"較上月減少 49.9%（改善趨勢）","value":8.16326530612245,"rule":"","reference_value":16.27906976744186,"year":110,"month":8},{"mechanism":"monthly_change","severity":"watch","direction":"unfavorable","message":"較上月增加 16.7%（不利方向）","value":9.523809523809524,"rule":"","reference_value":8.16326530612245,"year":110,"month":9},{"mechanism":"monthly_change","severity":"excellent","direction":"favorable","message":"較上月減少 57.1%（改善趨勢）","value":4.081632653061225,"rule":"","reference_value":9.523809523809524,"year":110,"month":10},{"mechanism":"monthly_change","severity":"watch","direction":"unfavorable","message":"較上月增加 59.8%（不利方向）","value":6.521739130434782,"rule":"","reference_value":4.081632653061225,"year":110,"month":11},{"mechanism":"monthly_change","severity":"watch","direction":"unfavorable","message":"較上月增加 59.7%（不利方向）","value":10.416666666666668,"rule":"","reference_value":6.521739130434782,"year":110,"month":12},{"mechanism":"monthly_change","severity":"excellent","direction":"favorable","message":"較上月減少 20.0%（改善趨勢）","value":8.333333333333332,"rule":"","reference_value":10.416666666666668,"year":111,"month":1},{"mechanism":"monthly_change","severity":"watch","direction":"unfavorable","message":"較上月增加 46.3%（不利方向）","value":12.195121951219512,"rule":"","reference_value":8.333333333333332,"year":111,"month":2},{"mechanism":"monthly_change","severity":"excellent","direction":"favorable","message":"較上月減少 10.3%（改善趨勢）","value":10.9375,"rule":"","reference_value":12.195121951219512,"year":111,"month":3},{"mechanism":"monthly_change","severity":"excellent","direction":"favorable","message":"較上月減少 30.7%（改善趨勢）","value":7.575757575757576,"rule":"","reference_value":10.9375,"year":111,"month":4},{"mechanism":"monthly_change","severity":"watch","direction":"unfavorable","message":"較上月增加 16.7%（不利方向）","value":9.210526315789473,"rule":"","reference_value":7.894736842105263,"year":111,"month":6},{"mechanism":"monthly_change","severity":"excellent","direction":"favorable","message":"較上月減少 15.4%（改善趨勢）","value":7.792207792207792,"rule":"","reference_value":9.210526315789473,"year":111,"month":7},{"mechanism":"monthly_change","severity":"watch","direction":"unfavorable","message":"較上月增加 50.0%（不利方向）","value":11.11111111111111,"rule":"","reference_value":7.4074074074074066,"year":111,"month":9},{"mechanism":"monthly_change","severity":"watch","direction":"unfavorable","message":"較上月增加 31.7%（不利方向）","value":14.634146341463413,"rule":"","reference_value":11.11111111111111,"year":111,"month":10},{"mechanism":"monthly_change","severity":"excellent","direction":"favorable","message":"較上月減少 72.3%（改善趨勢）","value":3.896103896103896,"rule":"","reference_value":14.084507042253522,"year":112,"month":2},{"mechanism":"monthly_change","severity":"watch","direction":"unfavorable","message":"較上月增加 185.2%（不利方向）","value":11.11111111111111,"rule":"","reference_value":3.896103896103896,"year":112,"month":3},{"mechanism":"monthly_change","severity":"excellent","direction":"favorable","message":"較上月減少 50.5%（改善趨勢）","value":5.4945054945054945,"rule":"","reference_value":11.11111111111111,"year":112,"month":4},{"mechanism":"monthly_change","severity":"watch","direction":"unfavorable","message":"較上月增加 95.0%（不利方向）","value":10.714285714285714,"rule":"","reference_value":5.4945054945054945,"year":112,"month":5},{"mechanism":"monthly_change","severity":"excellent","direction":"favorable","message":"較上月減少 50.4%（改善趨勢）","value":5.319148936170213,"rule":"","reference_value":10.714285714285714,"year":112,"month":6},{"mechanism":"monthly_change","severity":"watch","direction":"unfavorable","message":"較上月增加 60.5%（不利方向）","value":8.536585365853659,"rule":"","reference_value":5.319148936170213,"year":112,"month":7},{"mechanism":"monthly_change","severity":"excellent","direction":"favorable","message":"較上月減少 63.4%（改善趨勢）","value":3.125,"rule":"","reference_value":8.536585365853659,"year":112,"month":8},{"mechanism":"monthly_change","severity":"watch","direction":"unfavorable","message":"較上月增加 52.4%（不利方向）","value":4.761904761904762,"rule":"","reference_value":3.125,"year":112,"month":9},{"mechanism":"monthly_change","severity":"watch","direction":"unfavorable","message":"較上月增加 79.3%（不利方向）","value":8.536585365853659,"rule":"","reference_value":4.761904761904762,"year":112,"month":10},{"mechanism":"monthly_change","severity":"watch","direction":"unfavorable","message":"較上月增加 10.8%（不利方向）","value":9.45945945945946,"rule":"","reference_value":8.536585365853659,"year":112,"month":11},{"mechanism":"monthly_change","severity":"excellent","direction":"favorable","message":"較上月減少 49.4%（改善趨勢）","value":5.0,"rule":"","reference_value":9.876543209876543,"year":113,"month":1},{"mechanism":"monthly_change","severity":"watch","direction":"unfavorable","message":"較上月增加 119.2%（不利方向）","value":10.95890410958904,"rule":"","reference_value":5.0,"year":113,"month":2},{"mechanism":"monthly_change","severity":"excellent","direction":"favorable","message":"較上月減少 39.8%（改善趨勢）","value":6.593406593406594,"rule":"","reference_value":10.95890410958904,"year":113,"month":3},{"mechanism":"monthly_change","severity":"watch","direction":"unfavorable","message":"較上月增加 37.9%（不利方向）","value":9.090909090909092,"rule":"","reference_value":6.593406593406594,"year":113,"month":4},{"mechanism":"monthly_change","severity":"excellent","direction":"favorable","message":"較上月減少 22.4%（改善趨勢）","value":7.0588235294117645,"rule":"","reference_value":9.090909090909092,"year":113,"month":5},{"mechanism":"monthly_change","severity":"excellent","direction":"favorable","message":"較上月減少 36.3%（改善趨勢）","value":4.49438202247191,"rule":"","reference_value":7.0588235294117645,"year":113,"month":6},{"mechanism":"monthly_change","severity":"watch","direction":"unfavorable","message":"較上月增加 90.7%（不利方向）","value":8.571428571428571,"rule":"","reference_value":4.49438202247191,"year":113,"month":7},{"mechanism":"monthly_change","severity":"watch","direction":"unfavorable","message":"較上月增加 84.2%（不利方向）","value":15.789473684210526,"rule":"","reference_value":8.571428571428571,"year":113,"month":8},{"mechanism":"monthly_change","severity":"excellent","direction":"favorable","message":"較上月減少 90.1%（改善趨勢）","value":1.5625,"rule":"","reference_value":15.789473684210526,"year":113,"month":9},{"mechanism":"monthly_change","severity":"watch","direction":"unfavorable","message":"較上月增加 350.7%（不利方向）","value":7.042253521126761,"rule":"","reference_value":1.5625,"year":113,"month":10},{"mechanism":"monthly_change","severity":"excellent","direction":"favorable","message":"較上月減少 31.3%（改善趨勢）","value":4.838709677419355,"rule":"","reference_value":7.042253521126761,"year":113,"month":11},{"mechanism":"monthly_change","severity":"watch","direction":"unfavorable","message":"較上月增加 72.2%（不利方向）","value":8.333333333333332,"rule":"","reference_value":4.838709677419355,"year":113,"month":12},{"mechanism":"monthly_change","severity":"excellent","direction":"favorable","message":"較上月減少 65.7%（改善趨勢）","value":2.857142857142857,"rule":"","reference_value":8.333333333333332,"year":114,"month":1},{"mechanism":"monthly_change","severity":"watch","direction":"unfavorable","message":"較上月增加 129.5%（不利方向）","value":6.557377049180328,"rule":"","reference_value":2.857142857142857,"year":114,"month":2},{"mechanism":"monthly_change","severity":"watch","direction":"unfavorable","message":"較上月增加 126.7%（不利方向）","value":14.864864864864865,"rule":"","reference_value":6.557377049180328,"year":114,"month":3},{"mechanism":"monthly_change","severity":"excellent","direction":"favorable","message":"較上月減少 50.5%（改善趨勢）","value":7.352941176470589,"rule":"","reference_value":14.864864864864865,"year":114,"month":4},{"mechanism":"monthly_change","severity":"watch","direction":"unfavorable","message":"較上月增加 94.3%（不利方向）","value":14.285714285714285,"rule":"","reference_value":7.352941176470589,"year":114,"month":5},{"mechanism":"monthly_change","severity":"excellent","direction":"favorable","message":"較上月減少 32.3%（改善趨勢）","value":9.67741935483871,"rule":"","reference_value":14.285714285714285,"year":114,"month":6},{"mechanism":"monthly_change","severity":"excellent","direction":"favorable","message":"較上月減少 49.2%（改善趨勢）","value":4.918032786885246,"rule":"","reference_value":9.67741935483871,"year":114,"month":7},{"mechanism":"monthly_change","severity":"watch","direction":"unfavorable","message":"較上月增加 112.4%（不利方向）","value":10.44776119402985,"rule":"","reference_value":4.918032786885246,"year":114,"month":8},{"mechanism":"monthly_change","severity":"watch","direction":"unfavorable","message":"較上月增加 14.9%（不利方向）","value":12.0,"rule":"","reference_value":10.44776119402985,"year":114,"month":9},{"mechanism":"monthly_change","severity":"excellent","direction":"favorable","message":"較上月減少 48.5%（改善趨勢）","value":6.329113924050633,"rule":"","reference_value":12.280701754385964,"year":114,"month":12},{"mechanism":"monthly_change","severity":"watch","direction":"unfavorable","message":"較上月增加 135.8%（不利方向）","value":14.925373134328357,"rule":"","reference_value":6.329113924050633,"year":115,"month":2},{"mechanism":"peer_comparison","severity":"watch","direction":"unfavorable","message":"高於同儕值 25.7%（同儕值: 11.87）","value":14.925373134328357,"rule":"","reference_value":11.87,"year":115,"month":2}],"control_chart":{"chart_type":"P","cl":8.562874251497005,"ucl":18.62615771512545,"lcl":0.0,"sigma":0,"ucl2":15.271729893915971,"lcl2":1.8540186090780404,"n":24,"variable_limits":[{"year":113,"month":3,"ucl":17.362650402074472,"lcl":0.0,"ucl2":14.429391685215318,"lcl2":2.6963568177786934,"sample_size":91},{"year":113,"month":4,"ucl":18.89572968081093,"lcl":0.0,"ucl2":15.451444537706289,"lcl2":1.6743039652877219,"sample_size":66},{"year":113,"month":5,"ucl":17.667935214774356,"lcl":0.0,"ucl2":14.632914893681905,"lcl2":2.4928336093121057,"sample_size":85},{"year":113,"month":6,"ucl":17.460974975066893,"lcl":0.0,"ucl2":14.494941400543597,"lcl2":2.6308071024504134,"sample_size":89},{"year":113,"month":7,"ucl":18.596162764758926,"lcl":0.0,"ucl2":15.251733260338286,"lcl2":1.8740152426557248,"sample_size":70},{"year":113,"month":8,"ucl":18.19197043204651,"lcl":0.0,"ucl2":14.982271705196675,"lcl2":2.1434767977973355,"sample_size":76},{"year":113,"month":9,"ucl":19.055938543659195,"lcl":0.0,"ucl2":15.5582504462718,"lcl2":1.5674980567222114,"sample_size":64},{"year":113,"month":10,"ucl":18.52525524364657,"lcl":0.0,"ucl2":15.204461579596716,"lcl2":1.921286923397295,"sample_size":71},{"year":113,"month":11,"ucl":19.223838233303105,"lcl":0.0,"ucl2":15.67018357270107,"lcl2":1.4555649302929403,"sample_size":62},{"year":113,"month":12,"ucl":18.455830140049414,"lcl":0.0,"ucl2":15.15817817719861,"lcl2":1.9675703257953998,"sample_size":72},{"year":114,"month":1,"ucl":18.596162764758926,"lcl":0.0,"ucl2":15.251733260338286,"lcl2":1.8740152426557248,"sample_size":70},{"year":114,"month":2,"ucl":19.31086795472683,"lcl":0.0,"ucl2":15.728203386983557,"lcl2":1.3975451160104537,"sample_size":61},{"year":114,"month":3,"ucl":18.321225828704527,"lcl":0.0,"ucl2":15.068441969635352,"lcl2":2.057306533358658,"sample_size":74},{"year":114,"month":4,"ucl":18.74264187808094,"lcl":0.0,"ucl2":15.349386002552961,"lcl2":1.7763625004410484,"sample_size":68},{"year":114,"month":5,"ucl":19.1388889593344,"lcl":0.0,"ucl2":15.6135507233886,"lcl2":1.51219777960541,"sample_size":63},{"year":114,"month":6,"ucl":19.223838233303105,"lcl":0.0,"ucl2":15.67018357270107,"lcl2":1.4555649302929403,"sample_size":62},{"year":114,"month":7,"ucl":19.31086795472683,"lcl":0.0,"ucl2":15.728203386983557,"lcl2":1.3975451160104537,"sample_size":61},{"year":114,"month":8,"ucl":18.818328924844543,"lcl":0.0,"ucl2":15.399844033728698,"lcl2":1.7259044692653136,"sample_size":67},{"year":114,"month":9,"ucl":20.4344213177599,"lcl":0.0,"ucl2":16.477238962338934,"lcl2":0.6485095406550778,"sample_size":50},{"year":114,"month":10,"ucl":18.89572968081093,"lcl":0.0,"ucl2":15.451444537706289,"lcl2":1.6743039652877219,"sample_size":66},{"year":114,"month":11,"ucl":19.681596795283113,"lcl":0.0,"ucl2":15.975355947354409,"lcl2":1.150392555639602,"sample_size":57},{"year":114,"month":12,"ucl":18.007369994497466,"lcl":0.0,"ucl2":14.859204746830645,"lcl2":2.266543756163366,"sample_size":79},{"year":115,"month":1,"ucl":18.007369994497466,"lcl":0.0,"ucl2":14.859204746830645,"lcl2":2.266543756163366,"sample_size":79},{"year":115,"month":2,"ucl":18.818328924844543,"lcl":0.0,"ucl2":15.399844033728698,"lcl2":1.7259044692653136,"sample_size":67}]},"peer_value":11.87}}